rss2gab/__init__.py
rss2gab/command.py
rss2gab/gab_readposts.py
rss2gab/parse_rss_feed.py
rss2gab/rss2gab.py
rss2gab/version.py
rss2gab-1.0.3.dist-info/METADATA
rss2gab-1.0.3.dist-info/WHEEL
rss2gab-1.0.3.dist-info/entry_points.txt
rss2gab-1.0.3.dist-info/top_level.txt
rss2gab-1.0.3.dist-info/RECORD
