Metadata-Version: 2.1
Name: rss2gab
Version: 1.0.3
Summary: Auto posts updates to the rss feed to gab
Home-page: https://github.com/zackees/rss2gab
Author: Zach Vorhies
Author-email: dont@email.me
License: MIT
Platform: UNKNOWN
Classifier: License :: OSI Approved :: MIT License
Classifier: Programming Language :: Python :: 3.6
Classifier: Programming Language :: Python :: 3.9
Classifier: Operating System :: Microsoft :: Windows
Classifier: Operating System :: POSIX
Classifier: Operating System :: MacOS :: MacOS X
Classifier: Environment :: Console
Requires-Python: >=3.6.0
Requires-Dist: gabposter (==1.2.8)
Requires-Dist: feedparser (==6.0.9)
Requires-Dist: garc (==2.1)
Requires-Dist: requests
Requires-Dist: moment
Provides-Extra: test
Requires-Dist: pytest ; extra == 'test'
